logfmt_pandas/__init__.py
logfmt_pandas/read.py
logfmt_pandas-0.1.2.dist-info/LICENSE
logfmt_pandas-0.1.2.dist-info/WHEEL
logfmt_pandas-0.1.2.dist-info/METADATA
logfmt_pandas-0.1.2.dist-info/RECORD
