Metadata-Version: 2.1
Name: logfmt-pandas
Version: 0.1.2
Summary: Read logfmt files into pandas dataframes.
Home-page: https://gitlab.com/link2xt/logfmt-pandas
License: MIT
Author: Alexander Krotov
Requires-Python: >=3.8,<4.0
Classifier: License :: OSI Approved :: MIT License
Classifier: Programming Language :: Python :: 3
Classifier: Programming Language :: Python :: 3.8
Requires-Dist: logfmt (>=0.4,<0.5)
Requires-Dist: pandas (>=1.0.4,<2.0.0)
Project-URL: Repository, https://gitlab.com/link2xt/logfmt-pandas
